{
  "video_id": "4XXGHzxfxI8",
  "title": "L'enchère la plus improbable (trop d'argent sérieux)",
  "url": "https://www.youtube.com/watch?v=4XXGHzxfxI8",
  "comment_count": 280,
  "comments": [
    {
      "author": "@SPuech",
      "author_id": "UCMQSwUNSnMOP4IRysfeg8EA",
      "text": "Vos retours sont comme d'habitude au top ! ⭐️\nPour une fois qu'une vidéo est \"feel good\" par ici haha. \nJe voulais encore une fois remercier Dashlane, et si leur service vous intéresse tout se passe ici : https://www.dashlane.com/simon ! 🔒",
      "likes": 81,
      "timestamp": 1640217600,
      "parent": "root",
      "is_reply": false
    },
    {
      "author": "@kyoyeou5899",
      "author_id": "UCPcjCnk3ZdWu2yHTJqrjQGw",
      "text": "Écran: Fait une taille\nSimon: Et si je mettais un plus petit écran sur leurs écrans",
      "likes": 640,
      "timestamp": 1640217600,
      "parent": "root",
      "is_reply": false
    },
    {
      "author": "@lucasmariller4603",
      "author_id": "UCuYrNkBb74Tyei3P3U8Ifrw",
      "text": "C’est comme ça que j’aime YouTube, c’est des vidéo intéressante et enrichissante. Ton boulot et extraordinaire. Bravo",
      "likes": 307,
      "timestamp": 1640217600,
      "parent": "root",
      "is_reply": false
    },
    {
      "author": "@valentinloirette7785",
      "author_id": "UC1sU0NfMvm25WXYsw0RZSmw",
      "text": "Certains s'appellent Pierre. Lui s'appelle 6:21",
      "likes": 110,
      "timestamp": 1640217600,
      "parent": "root",
      "is_reply": false
    },
    {
      "author": "@Sandozprod",
      "author_id": "UCnC8KCcp2-DYfPY4_bKIc0A",
      "text": "Histoire de dingue tout de même, vidéo très intéressante merci pour tout ça.",
      "likes": 365,
      "timestamp": 1640217600,
      "parent": "root",
      "is_reply": false
    },
    {
      "author": "@gautierc.275",
      "author_id": "UCBcg0cTPXjny394l6q4SNCQ",
      "text": "Ta façon de raconter des histoires et le montage ultra dynamique avec des illustrations simples mais hyper efficaces ça rend tes vidéos complètement uniques. j'aimerais tellement avoir ça sur ma propre chaine. Ça + les sujets qui sont extrêmement intéressants, c'est assez fou.",
      "likes": 44,
      "timestamp": 1640217600,
      "parent": "root",
      "is_reply": false
    },
    {
      "author": "@MrSifless",
      "author_id": "UCOw4Y77oWSAW_yEVoO2yffw",
      "text": "\"les jeunes français français dansent comme des décoration d'autoroute\"\n\nPause PLS pour moi. ça m'a tué.",
      "likes": 29,
      "timestamp": 1640217600,
      "parent": "root",
      "is_reply": false
    },
    {
      "author": "@L7luckyseven",
      "author_id": "UCdsYGT0X82DHAJtZN6KVOFQ",
      "text": "Je me mange absolument toute les vidéos de ta chaîne, j’ai l’impression d’avoir trouver la série du siècle, merci pour ce boulot de ouf!",
      "likes": 5,
      "timestamp": 1734912000,
      "parent": "root",
      "is_reply": false
    },
    {
      "author": "@QuentinDecaunes",
      "author_id": "UC8TIs9IeeOFiykyXGq8s_Mg",
      "text": "Pas d'intro, pas d'outro, direct l'essentiel\n\nJ'aime",
      "likes": 11,
      "timestamp": 1640217600,
      "parent": "root",
      "is_reply": false
    },
    {
      "author": "@MIl_O",
      "author_id": "UCyKC1KeJzQ0y6SpNqiDU5bA",
      "text": "Vraiment toutes ses vidéos sont intéressantes c'est fou",
      "likes": 86,
      "timestamp": 1640217600,
      "parent": "root",
      "is_reply": false
    },
    {
      "author": "@mateolalanne8708",
      "author_id": "UCKHJjFRL8dSi86RQnwxde-g",
      "text": "A chaque fin de vidéo j'ai envie de pleurer, je sais pas si c'est parce que c'est fini ou parce que c'est une masterclass à chaque fois... mais sah t'es trop fort",
      "likes": 84,
      "timestamp": 1640217600,
      "parent": "root",
      "is_reply": false
    },
    {
      "author": "@MrKazRoll",
      "author_id": "UCyabIIm5bYkmfDsQfGnR3XA",
      "text": "Des barres, le google de mon téléphone s'est réveillé à 3:36 xD chui mort",
      "likes": 12,
      "timestamp": 1640217600,
      "parent": "root",
      "is_reply": false
    },
    {
      "author": "@Streethagore",
      "author_id": "UCPSg2anrYSrDiqyPobe9YiQ",
      "text": "Je suis dans le deep learning et... Ouais tu lui as bien rendu hommage 👌",
      "likes": 111,
      "timestamp": 1640217600,
      "parent": "root",
      "is_reply": false
    },
    {
      "author": "@ArsenalDuTemps",
      "author_id": "UC-dWvenKiUTUkWxY7FXIC0g",
      "text": "toujours aussi poignantes tes vidéos, GG à toi :)",
      "likes": 28,
      "timestamp": 1640217600,
      "parent": "root",
      "is_reply": false
    },
    {
      "author": "@wiwiza7436",
      "author_id": "UC74Ltr__Af-aEHsnwCmvSnA",
      "text": "3:32 wesh moi aussi mon assistant Google c'est activé mdr",
      "likes": 2,
      "timestamp": 1640217600,
      "parent": "root",
      "is_reply": false
    },
    {
      "author": "@Jus2Fruit",
      "author_id": "UCeO2w69qwLgOSoiK9bfIVxQ",
      "text": "6:20 KAYOUUUUUU",
      "likes": 1,
      "timestamp": 1734912000,
      "parent": "root",
      "is_reply": false
    },
    {
      "author": "@moijenaimepasrenseignermes5887",
      "author_id": "UCGpIG-Uv3SGqHQP5rKatgSA",
      "text": "\"Your flesh is a relic; a mere vessel. Hand over your flesh, and a new world awaits you. We demand it\"",
      "likes": 15,
      "timestamp": 1640217600,
      "parent": "root",
      "is_reply": false
    },
    {
      "author": "@d3lta-cc",
      "author_id": "UCuC-m-YQO7C-34AdFVicaMA",
      "text": "Si il avait su que aujourd’hui chat gpt existe il aurait peter les plombs",
      "likes": 1,
      "timestamp": 1734912000,
      "parent": "root",
      "is_reply": false
    },
    {
      "author": "@titi12fev",
      "author_id": "UCvqDDubd2KW24gBmtsF0cKQ",
      "text": "Rien à voir, mais au début j'ai juste lu le titre et je pensais qu'il allait parler de Lorenzo et ses cartes Pokémon",
      "likes": 5,
      "timestamp": 1640217600,
      "parent": "root",
      "is_reply": false
    },
    {
      "author": "@neyrozzz",
      "author_id": "UCdQKmDaI4bw2fGbFzKZ5HBg",
      "text": "(même les pharmaciens n'arrivent pas toujours à lire les écritures des médecins, il y a des milliers de morts chaque année à cause d'une mauvaise lecture de la prescription)",
      "likes": 3,
      "timestamp": 1640217600,
      "parent": "root",
      "is_reply": false
    },
    {
      "author": "@titouansom",
      "author_id": "UCh5DIy9TM4oXV8VksUlYuog",
      "text": "Fun fact, si l'assistant Google s'active sans qu'on le veuille, et que vous lui dites \"nan c'est pas a toi que je parles\", il répondra alors \"très bien, je supprime ce que je viens d'entendre\"... Bon",
      "likes": 2,
      "timestamp": 1640217600,
      "parent": "root",
      "is_reply": false
    },
    {
      "author": "@MrAupire",
      "author_id": "UCw22uk4eq8LfsC6eKx8ZTyg",
      "text": "J'ai pris un coup de vieux quand je l'ai entendu dire SWAG ...",
      "likes": 1,
      "timestamp": 1671753600,
      "parent": "root",
      "is_reply": false
    },
    {
      "author": "@bordcharly8215",
      "author_id": "UCMa8XIHSV0Laru4F_bv92_g",
      "text": "je viens de découvrir la chaine, le contenu est incroyable",
      "likes": 1,
      "timestamp": 1640217600,
      "parent": "root",
      "is_reply": false
    },
    {
      "author": "@Antoinevi",
      "author_id": "UCJzowJt5a0J38pmCUvLKNDA",
      "text": "ça met des frissons tellement c'est beau",
      "likes": 0,
      "timestamp": 1703289600,
      "parent": "root",
      "is_reply": false
    },
    {
      "author": "@ldcjmp737",
      "author_id": "UCarwYlL0EHB6yuYTZx08aZQ",
      "text": "Tu racontes vachement bien les histoires, même si on y connait rien, on est obligé d'avancer dans la vidéo pour finalement comprendre que tu as encore choisi un sujet que nous utilisons tous les jours ! Merci Simon",
      "likes": 1,
      "timestamp": 1640217600,
      "parent": "root",
      "is_reply": false
    },
    {
      "author": "@lespepitesdesjeuxvideo8526",
      "author_id": "UC0FFYsLtLokuQjowPQWPbHQ",
      "text": "Il faudrait en faire un film de cette histoire\nSobrement appelé : 731 ou chambre 731",
      "likes": 2,
      "timestamp": 1640217600,
      "parent": "root",
      "is_reply": false
    },
    {
      "author": "@benjaminbodinaud1213",
      "author_id": "UC2y7VDM4VJO3Y6ACNA6WRWw",
      "text": "Superbe success story, qu'il ne fallait pas laisser inconnu du grand public, très inspirante. Excellente vidéo !",
      "likes": 0,
      "timestamp": 1640217600,
      "parent": "root",
      "is_reply": false
    },
    {
      "author": "@cocowondering",
      "author_id": "UCsHt4ijNUppkXyz4FvoBxcA",
      "text": "7:39 Bienvenue dans Love, Death & Robot",
      "likes": 1,
      "timestamp": 1640217600,
      "parent": "root",
      "is_reply": false
    },
    {
      "author": "@stoxca",
      "author_id": "UC5_gu29Kz9UKZnDC-vNWXUQ",
      "text": "c'est incroyable cette histoire",
      "likes": 0,
      "timestamp": 1640217600,
      "parent": "root",
      "is_reply": false
    },
    {
      "author": "@HDMVlaura",
      "author_id": "UC-5ybc7bKIvs8W3xQY3cT1A",
      "text": "\"il a refusé de s'asseoir sur ses convictions\" souffle fort du nez",
      "likes": 5,
      "timestamp": 1640217600,
      "parent": "root",
      "is_reply": false
    },
    {
      "author": "@JulienMonthioux",
      "author_id": "UCSu6qYFh6_CWGfNIb2yo2FQ",
      "text": "Tellement sous cotée ta chaîne Simon !",
      "likes": 0,
      "timestamp": 1671753600,
      "parent": "root",
      "is_reply": false
    },
    {
      "author": "@StanleyMernet",
      "author_id": "UCQp_dEOorAB4ZDsJ0lfU6EA",
      "text": "Simon Puech. Rien à dire d’autre.",
      "likes": 0,
      "timestamp": 1640217600,
      "parent": "root",
      "is_reply": false
    },
    {
      "author": "@phil_marshall",
      "author_id": "UClEgK5nnUqT4OeSU3HAoyUg",
      "text": "incroyable la méthaphore du début",
      "likes": 0,
      "timestamp": 1640217600,
      "parent": "root",
      "is_reply": false
    },
    {
      "author": "@elefantsoul787",
      "author_id": "UC8KozP6ORSH50yXcKy6dOYg",
      "text": "Ça c sûr qu’il peut pas s’assoir sur ses convictions mais il peut quand même rester debout",
      "likes": 1,
      "timestamp": 1640217600,
      "parent": "root",
      "is_reply": false
    },
    {
      "author": "@king-uy1lv",
      "author_id": "UC3LYgvnr9QpOKzPVn7gmkLQ",
      "text": "Salut j'ai pas encore regarder la vidéo mais je voulais dire que tu fais du super taff je respecte ton intégrité et j'aime beaucoup c'que tu fait !",
      "likes": 7,
      "timestamp": 1640217600,
      "parent": "root",
      "is_reply": false
    },
    {
      "author": "@membalev6885",
      "author_id": "UCecElGNQMLStLP7IxO33QOw",
      "text": "Ca rappelle le premier épisode d'Amazon's Utopia",
      "likes": 0,
      "timestamp": 1640217600,
      "parent": "root",
      "is_reply": false
    },
    {
      "author": "@amaurycolez1406",
      "author_id": "UCj9z7M6PWlNnUTANf-Fci5w",
      "text": "J'ai rigolé au nom du mnsieur de Bai Du.\n\"Chez nous à la maison,\r\nc'est moi le grand garçon,\r\nj'aime ça toucher à tout j'm'appelle Kai yu\r\n\r\nAutour de moi c'est tellement beau,\r\ntout les jours y a du nouveau,\r\nj'trouve des amis partout\r\nj'm'appelle Kai yu\"",
      "likes": 1,
      "timestamp": 1640217600,
      "parent": "root",
      "is_reply": false
    },
    {
      "author": "@chantreazur7921",
      "author_id": "UCVvpQHoLYGh3FtKQPb46Cgg",
      "text": "Il s'est assis sur tellement d'argent en arrêtant les enchères !!!",
      "likes": 1,
      "timestamp": 1640217600,
      "parent": "root",
      "is_reply": false
    },
    {
      "author": "@Yomalan_gfx",
      "author_id": "UC6i2JNZywczSzLmZrir4ozw",
      "text": "Meilleur storytelling",
      "likes": 0,
      "timestamp": 1640217600,
      "parent": "root",
      "is_reply": false
    },
    {
      "author": "@medi507",
      "author_id": "UCbuxO9JJ155aFZ4r8Maoqdg",
      "text": "Cette vidéo à bien vieillît",
      "likes": 0,
      "timestamp": 1734912000,
      "parent": "root",
      "is_reply": false
    },
    {
      "author": "@sylphus",
      "author_id": "UCPQ74IpJJP32gD7iqFFZKlg",
      "text": "Salut, je binge watch tes vidéos.",
      "likes": 1,
      "timestamp": 1703289600,
      "parent": "root",
      "is_reply": false
    },
    {
      "author": "@serignembayethiam3976",
      "author_id": "UC_dWiNs_Roj3OvxTSTNghsA",
      "text": "Mec t'es ouf j'adore ta manière de dérouler.",
      "likes": 0,
      "timestamp": 1640217600,
      "parent": "root",
      "is_reply": false
    },
    {
      "author": "@EliottAndreSavolle",
      "author_id": "UChSt5X4rbSuzbt5UKa1OUXw",
      "text": "6:19 Kai yu jsuis PTDRR 🪨",
      "likes": 1,
      "timestamp": 1703289600,
      "parent": "root",
      "is_reply": false
    },
    {
      "author": "@frankcisde2338",
      "author_id": "UClF6xofGj-o5-c3EVUlaEfQ",
      "text": "Captivant du début à la fin, comme d’habitude",
      "likes": 0,
      "timestamp": 1640217600,
      "parent": "root",
      "is_reply": false
    },
    {
      "author": "@marinslim283",
      "author_id": "UCcFgyv8RNKRMrSom5PVBi4Q",
      "text": "rien compris mais réel",
      "likes": 1,
      "timestamp": 1640217600,
      "parent": "root",
      "is_reply": false
    },
    {
      "author": "@SkyeLancaster",
      "author_id": "UCFFuozFpB02eNiJ2i4C3EVg",
      "text": "Merci de faire des vidéos de ce genre et d'une telle qualité. Je n'y connais honnêtement pas grand chose mais ta façon de raconter les choses est super captivante 👌",
      "likes": 0,
      "timestamp": 1640217600,
      "parent": "root",
      "is_reply": false
    },
    {
      "author": "@ptitetomate8941",
      "author_id": "UCR1w2sKtLWJAR53HZ1aQvWw",
      "text": "J'aimerais vraiment que tu fasses une vidéo pour expliquer aux gens que les mathématiques régissent le monde entier via la physique et la chimie et que toutes les autres sciences n'en sont que des dérivées; aussi parler du lien de parenté entre les maths et la philosophie pourrait être intéressant. Je te conseille les vidéos de science4all pour en savoir un peu plus, car son travail à eu plus d'impact sur mon raisonnement que n'importe quel autre énonciateur (j adore ton travail aussi tkt). Je te conseillerai même de le contacter sur les réseaux pour qu'il puisse te conseiller. Ça pourrait être une tuerie comme vidéo avec ton style.",
      "likes": 0,
      "timestamp": 1640217600,
      "parent": "root",
      "is_reply": false
    },
    {
      "author": "@Malo_Crnl",
      "author_id": "UCcY2oJLIAKa8_Qtt2SwgSiQ",
      "text": "Quel crack ce Geoff",
      "likes": 0,
      "timestamp": 1640217600,
      "parent": "root",
      "is_reply": false
    },
    {
      "author": "@timomuller94",
      "author_id": "UCAv0LejAQoJMq2t560TRCJg",
      "text": "c'est bien beau tout ça mais moi je me demande comment le type se lève de son lit et chie sans s'assoir ??",
      "likes": 1,
      "timestamp": 1640217600,
      "parent": "root",
      "is_reply": false
    },
    {
      "author": "@Ludodo",
      "author_id": "UCWfJb5C09azPRdXsgoV6JQQ",
      "text": "vraiment beau le message final",
      "likes": 0,
      "timestamp": 1640217600,
      "parent": "root",
      "is_reply": false
    },
    {
      "author": "@avisdunrandom",
      "author_id": "UCRpzMCdAE7k7xqG7doFzMGA",
      "text": "Le flex du monsieur.",
      "likes": 0,
      "timestamp": 1640217600,
      "parent": "root",
      "is_reply": false
    },
    {
      "author": "@ze_nox__1444",
      "author_id": "UCnjmmbiswdjqMC_77qCxQLg",
      "text": "L’histoire est incroyable",
      "likes": 0,
      "timestamp": 1640217600,
      "parent": "root",
      "is_reply": false
    },
    {
      "author": "@Matosh",
      "author_id": "UCL28F3HQ6qOuMsW9lZKC7uA",
      "text": "Tu sais Simon je met toujours un pouce bleu avant meme de commencer la vidéo mais sur beaucoup d'entre elles j'ai envie d'en remettre un quand j'ai fini la vidéo un grand merci pour ton taf bisous et force a toi.",
      "likes": 2,
      "timestamp": 1640217600,
      "parent": "root",
      "is_reply": false
    },
    {
      "author": "@PlasticTounu",
      "author_id": "UCaZXHUwPDvQpHyk-QcVaK0A",
      "text": "Quand c'est ton taff de tous les jours qui offre des histoires comme ça, whololo",
      "likes": 0,
      "timestamp": 1640217600,
      "parent": "root",
      "is_reply": false
    },
    {
      "author": "@iamdragonkrys",
      "author_id": "UCOwQknOz5YkhXJYR_o4HpQA",
      "text": "Tu es le YouTuber le plus génial",
      "likes": 0,
      "timestamp": 1671753600,
      "parent": "root",
      "is_reply": false
    },
    {
      "author": "@wakly562",
      "author_id": "UCDpfIhKswXfGS2PCqjWvc8w",
      "text": "j'adore tes vidéos qui sont si paisible...",
      "likes": 1,
      "timestamp": 1640217600,
      "parent": "root",
      "is_reply": false
    },
    {
      "author": "@so2nyme",
      "author_id": "UC348DWVJ3VKR4BBeauuznTA",
      "text": "\" un certain.. caillou\"",
      "likes": 0,
      "timestamp": 1640217600,
      "parent": "root",
      "is_reply": false
    },
    {
      "author": "@enockhouessou1874",
      "author_id": "UCgtqfs-EIoNR_OYsjoyqKsw",
      "text": "une histoire folle",
      "likes": 0,
      "timestamp": 1671753600,
      "parent": "root",
      "is_reply": false
    },
    {
      "author": "@maximegiguere4621",
      "author_id": "UCO8BRS1LuWn8BLYoUiCux0g",
      "text": "Morale de l'histoire, continuez de vous battre pour vos convictions. Même si des géants vous disent que c'est impossible.",
      "likes": 0,
      "timestamp": 1640217600,
      "parent": "root",
      "is_reply": false
    },
    {
      "author": "@iloooveBOMBS",
      "author_id": "UClTqoWL-SXj2dW0QvSaa8ig",
      "text": "Super intéressant, super bien monté, juste génial !",
      "likes": 2,
      "timestamp": 1640217600,
      "parent": "root",
      "is_reply": false
    },
    {
      "author": "@antoineg3362",
      "author_id": "UCAVuMqgLfu6NAUJgJzUkPQg",
      "text": "Incroyable. Super vidéo, je suis venu suite à celle sur les paradis fiscaux, superbe découverte !",
      "likes": 0,
      "timestamp": 1640217600,
      "parent": "root",
      "is_reply": false
    },
    {
      "author": "@erwancp1553",
      "author_id": "UC-kiRst27rd_CN4MQiNZgiA",
      "text": "4:50 meilleur fou rire de ma vie",
      "likes": 0,
      "timestamp": 1640217600,
      "parent": "root",
      "is_reply": false
    },
    {
      "author": "@Awaide",
      "author_id": "UC3K0j1y_Y51LTPeHBSloLrg",
      "text": "à chaque fois je termine la vidéo accompagné d'un petit frisson. Merci Simon pour ton travail !",
      "likes": 0,
      "timestamp": 1640217600,
      "parent": "root",
      "is_reply": false
    },
    {
      "author": "@alexcupp3600",
      "author_id": "UCUnuNefRar_yux4wfReUqDw",
      "text": "la chaîne la plus sous cotée du YT game",
      "likes": 0,
      "timestamp": 1640217600,
      "parent": "root",
      "is_reply": false
    },
    {
      "author": "@paulfrarier9586",
      "author_id": "UCwtAyr9HRcOJdTsz6BgU8Gw",
      "text": "Tu sais nous raconter ça c'est incroyable ! l'ambiance de tes vidéo et l'étincelle dans tes yeux me captive à chaque fois ! Merci !",
      "likes": 0,
      "timestamp": 1640217600,
      "parent": "root",
      "is_reply": false
    },
    {
      "author": "@Piway33",
      "author_id": "UCi_kVSLQgEaADsKCvTbIeFQ",
      "text": "Bien joué mon pote. T’es en tendance c’est mérité",
      "likes": 0,
      "timestamp": 1640217600,
      "parent": "root",
      "is_reply": false
    },
    {
      "author": "@DixonStJhon44H57",
      "author_id": "UCnjQc-YP4yPBw-kHs0yUrQw",
      "text": "Une détermination inhumaine",
      "likes": 0,
      "timestamp": 1640217600,
      "parent": "root",
      "is_reply": false
    },
    {
      "author": "@aydanlakhmiri2349",
      "author_id": "UCLxlcJGK4RO8ylcNR7-aQWw",
      "text": "Quand t'as dit Ok mon google nest c'est aussi activé",
      "likes": 0,
      "timestamp": 1640217600,
      "parent": "root",
      "is_reply": false
    },
    {
      "author": "@ced6528",
      "author_id": "UC26wwivIzDMzHieTYvLxTNA",
      "text": "La narration au top, merci",
      "likes": 0,
      "timestamp": 1640217600,
      "parent": "root",
      "is_reply": false
    },
    {
      "author": "@gdefoz",
      "author_id": "UCmITnvPstKyKonzjkfiElYw",
      "text": "La Singularité fait peur..mais avec des types comme hilton on peut avoir de l'espoir",
      "likes": 0,
      "timestamp": 1640217600,
      "parent": "root",
      "is_reply": false
    },
    {
      "author": "@sn0wflakeash3s73",
      "author_id": "UCUKSH2yjUVeqXRp55nsUZLw",
      "text": "Toujours super inspirantes les vidéos sur cette chaîne merci bcp",
      "likes": 0,
      "timestamp": 1640217600,
      "parent": "root",
      "is_reply": false
    },
    {
      "author": "@dinoman3594",
      "author_id": "UC20L8dXbWBQRMv-A9AO1SDQ",
      "text": "Quesque je kiff tes vidéos c'est fou !\nBien que la singularité qui va être créé pourra servir de bonne choses ou de mauvaises , elle reste notre avenir et c'est à nous quelle puisse nous guider et résoudre les problèmes fondamentaux de l'humanité .",
      "likes": 1,
      "timestamp": 1640217600,
      "parent": "root",
      "is_reply": false
    },
    {
      "author": "@jockdepal5147",
      "author_id": "UC_oHL7p-LxCOSkSInoL_NJQ",
      "text": "Petit commentaire pour le référencement et la qualité de narration !",
      "likes": 0,
      "timestamp": 1640217600,
      "parent": "root",
      "is_reply": false
    },
    {
      "author": "@JKhan-rl1xg",
      "author_id": "UCplE9hhw9DCNFAUrU-mxWrg",
      "text": "C'était passionnant comme vidéo, bravo Simon",
      "likes": 0,
      "timestamp": 1640217600,
      "parent": "root",
      "is_reply": false
    },
    {
      "author": "@razou2257",
      "author_id": "UC6fOICbK1eRmeb_y5vjA_AQ",
      "text": "incroyable vidéo j'ai palpité",
      "likes": 0,
      "timestamp": 1640217600,
      "parent": "root",
      "is_reply": false
    },
    {
      "author": "@WingSun",
      "author_id": "UCw0zvjxn05q9wr6CabZplHw",
      "text": "Pas convaincu par la singularité qui me paraît plus un mythe qu’autre chose, mais intéressant !",
      "likes": 2,
      "timestamp": 1640217600,
      "parent": "root",
      "is_reply": false
    },
    {
      "author": "@Feajyal",
      "author_id": "UCIszuIzt99q9y9UZlc0k8oQ",
      "text": "Mdr à 3:31 tu as aussi réveillé mon téléphone (un Pixel) la preuve que ça fonctionne, j'ai sursauté devant ce brisage de quatrième mur",
      "likes": 3,
      "timestamp": 1640217600,
      "parent": "root",
      "is_reply": false
    },
    {
      "author": "@TheDrzoidberg92",
      "author_id": "UCseP8OeLEwq5wSTUzzzd5QA",
      "text": "video niquel comme d'hab frero",
      "likes": 0,
      "timestamp": 1640217600,
      "parent": "root",
      "is_reply": false
    },
    {
      "author": "@kenshindu49",
      "author_id": "UCn9gOlYLIbKcOVBc8sKogXA",
      "text": "Super vidéo encore une fois 👏 Le petit rappel de Stephan Thomas qui fait plaisir 😂",
      "likes": 0,
      "timestamp": 1640217600,
      "parent": "root",
      "is_reply": false
    },
    {
      "author": "@ostycream",
      "author_id": "UCVCQv46og-M7KAqB2SceLsA",
      "text": "OMG une vidéo pour la journée de ma fête, ta fait ma journée!",
      "likes": 0,
      "timestamp": 1640217600,
      "parent": "root",
      "is_reply": false
    },
    {
      "author": "@MrBibimo",
      "author_id": "UC2f0ESwD3JO5aYHq7Tz2ZUA",
      "text": "Avoir des burnes et ne jamais risquer de s'assoir dessus: définition !",
      "likes": 0,
      "timestamp": 1640217600,
      "parent": "root",
      "is_reply": false
    },
    {
      "author": "@mathieuribeaud6837",
      "author_id": "UCYunzVmnBwOBDaf1i7vZQSw",
      "text": "Super vidéo, comme toujours !",
      "likes": 0,
      "timestamp": 1640217600,
      "parent": "root",
      "is_reply": false
    },
    {
      "author": "@gourmont4726",
      "author_id": "UCT9hc-LKnqO-XCOO05RKe9Q",
      "text": "4:49 ah bordel ça m'a fait trop rire. 😂",
      "likes": 0,
      "timestamp": 1703289600,
      "parent": "root",
      "is_reply": false
    },
    {
      "author": "@cypri1101",
      "author_id": "UC_uBu7dJJN7V1j3s3QCTrvw",
      "text": "Magnifique vidéo, bien résumé, bien illustré !",
      "likes": 0,
      "timestamp": 1640217600,
      "parent": "root",
      "is_reply": false
    },
    {
      "author": "@lilbak1056",
      "author_id": "UC6zCxCKXyk8Nxw-N1YtatIQ",
      "text": "Tu vas percer mec c'est sur ! Tes vidéos sont géniales",
      "likes": 0,
      "timestamp": 1640217600,
      "parent": "root",
      "is_reply": false
    },
    {
      "author": "@cedriccanton",
      "author_id": "UCee5BJasmX9L3ocDNkL29Iw",
      "text": "Une masterclass, bravo et merci Simon",
      "likes": 0,
      "timestamp": 1640217600,
      "parent": "root",
      "is_reply": false
    },
    {
      "author": "@ValtielArch",
      "author_id": "UCFpgXvVOnwy_xDVeghUWQNA",
      "text": "Le moment où t'as activé ton assistant Google, ça a aussi activé le miens x)",
      "likes": 0,
      "timestamp": 1640217600,
      "parent": "root",
      "is_reply": false
    },
    {
      "author": "@i.l.l.u.s.i.o.n.s",
      "author_id": "UCOJB-XEUIjmnWC0oW8sVgNQ",
      "text": "toujours aussi intéressant",
      "likes": 0,
      "timestamp": 1640217600,
      "parent": "root",
      "is_reply": false
    },
    {
      "author": "@Reshv1",
      "author_id": "UCV9DR__OH2kq3ZBCctDu5DA",
      "text": "Je suis vraiment impressionner à chaque vidéo par ton storytelling . Aurait tu des personne ou des livres qui t'on inspirer et aider à améliorer cette compétence ? Encore une fois gg , superbe vidéo !",
      "likes": 1,
      "timestamp": 1640217600,
      "parent": "root",
      "is_reply": false
    },
    {
      "author": "@sebastienblois7876",
      "author_id": "UCT1eZMR8v1u4rB55jvf7odQ",
      "text": "De la folie cette vidéo comme toujours !!",
      "likes": 0,
      "timestamp": 1640217600,
      "parent": "root",
      "is_reply": false
    },
    {
      "author": "@Maisjensaistoujoursrienmoiomg",
      "author_id": "UCEovInX43VYtvvLYqw1-V0w",
      "text": "Comme d'habitude, c'est super intéressant et super bien raconté !",
      "likes": 0,
      "timestamp": 1640217600,
      "parent": "root",
      "is_reply": false
    },
    {
      "author": "@titouanguithou6046",
      "author_id": "UCYeYI_2ZXYT-G6gxOJ6rg_A",
      "text": "Sur ton Twitch on nourrit ton égo en regardant des simili-chrono mdrr grosse ambiance quand même",
      "likes": 14,
      "timestamp": 1640217600,
      "parent": "root",
      "is_reply": false
    },
    {
      "author": "@adnxy6581",
      "author_id": "UCvV2V4TxfxMo0da_PAPXO7A",
      "text": "Merci 🎥",
      "likes": 0,
      "timestamp": 1640217600,
      "parent": "root",
      "is_reply": false
    },
    {
      "author": "@bocobzaperle1637",
      "author_id": "UC7OUWnZhh6rWv2ccOlgAkzQ",
      "text": "Autant flippant que passionnant.",
      "likes": 0,
      "timestamp": 1640217600,
      "parent": "root",
      "is_reply": false
    },
    {
      "author": "@MrYoshi58",
      "author_id": "UC3NWinJu2iR602VR0sGiF3Q",
      "text": "Vidéo incroyable",
      "likes": 0,
      "timestamp": 1640217600,
      "parent": "root",
      "is_reply": false
    },
    {
      "author": "@Théo-Delamare",
      "author_id": "UCI8pSulO2j9q0If-H_SzFBA",
      "text": "yes, je prendrais plus de recule sur l'idée que la singularité est un moment bien précis et unique\nIl s'agit plutôt d'une transition à moyen terme que l'on a déjà bien entamé et qui se fait sous des formes très différentes à plusieurs endroits en même temps, les algos des réseaux sociaux, les assistants etc..\nLà où on peut difficilement anticiper le phénomène c'est surtout sur la forme sûrement très différente d'un esprit humain que ça va prendre.",
      "likes": 0,
      "timestamp": 1640217600,
      "parent": "root",
      "is_reply": false
    },
    {
      "author": "@kaceymill",
      "author_id": "UC_AxJ5shr-f8E-a58CZEkBw",
      "text": "Pourquoi tu as changé le titre de la vidéo? \n(C'était Il a vendu l'avenir aux enchères)",
      "likes": 4,
      "timestamp": 1640217600,
      "parent": "root",
      "is_reply": false
    },
    {
      "author": "@valenwed",
      "author_id": "UCX8gxzo8au6FGDXG042gyEg",
      "text": "4:49 Comme des décos d'autoroutes xD",
      "likes": 0,
      "timestamp": 1640217600,
      "parent": "root",
      "is_reply": false
    },
    {
      "author": "@hummbobyhumm",
      "author_id": "UClDYMgvJF1Bcck1RU15EX2g",
      "text": "toujours au top!! le rythme, l'intonation, l'AI qui réagit au 1/4 de tour :) bref Continu",
      "likes": 0,
      "timestamp": 1640217600,
      "parent": "root",
      "is_reply": false
    },
    {
      "author": "@moxinex1696",
      "author_id": "UCVXdZ7UpV3zlSXpsClqQFFg",
      "text": "Masterclass",
      "likes": 0,
      "timestamp": 1640217600,
      "parent": "root",
      "is_reply": false
    },
    {
      "author": "@ugo8862",
      "author_id": "UCSrUkyNPZ7OkTxPCAk65dPg",
      "text": "Drôle de Monsieur ou quoi làààà",
      "likes": 0,
      "timestamp": 1640217600,
      "parent": "root",
      "is_reply": false
    },
    {
      "author": "@jeanmionnet8084",
      "author_id": "UCkEhL7m9A-r9_zBeaduQCKA",
      "text": "Un certain caillou.",
      "likes": 0,
      "timestamp": 1640217600,
      "parent": "root",
      "is_reply": false
    },
    {
      "author": "@Le-4-orze",
      "author_id": "UCVluD-2xyZ4J3dzOhiZJ7ew",
      "text": "Jamais tombé sur ta chaîne pourtant je regarde énormément de vidéos sur le trans humanisme, l’IA bottom up, le deep learning et en général ce qui touche au futur technologique. Tu es très bon je m’abonne !",
      "likes": 2,
      "timestamp": 1640217600,
      "parent": "root",
      "is_reply": false
    },
    {
      "author": "@sachadamon3536",
      "author_id": "UCSuvMH36xSDLwkacZiAKQMg",
      "text": "Encore une vidéo trop cool !",
      "likes": 1,
      "timestamp": 1640217600,
      "parent": "root",
      "is_reply": false
    },
    {
      "author": "@nixotane9660",
      "author_id": "UCCtU-aZ-3nAhsYp2E9fnOVw",
      "text": "Acheté toi une secretlab, c'est cher mais ton dos te diras merci. Ils viennent de dévoilé leur modèles 2022 ils sont vraiment top",
      "likes": 0,
      "timestamp": 1640217600,
      "parent": "root",
      "is_reply": false
    },
    {
      "author": "@pierresilbermann605",
      "author_id": "UCRiU2uyb1bZz8fWHZydvikw",
      "text": "Incroyable",
      "likes": 0,
      "timestamp": 1640217600,
      "parent": "root",
      "is_reply": false
    },
    {
      "author": "@alexis5426",
      "author_id": "UCpIBLswNDTCGWEnCktIVpXQ",
      "text": "T'es vidéo sont de mieux en mieux continue comme sa tu propose des sujets très srx bravo a toi",
      "likes": 0,
      "timestamp": 1640217600,
      "parent": "root",
      "is_reply": false
    },
    {
      "author": "@dala7941",
      "author_id": "UCN62ILob3C0ZGWtI0ypomGQ",
      "text": "pk tout tes sujets font rêver comme ça ?  Simon pourrait nous décrire des excréments qu'a la dernière minute de sa vidéo on serait en mode \"A oue, incroyable\"",
      "likes": 0,
      "timestamp": 1640217600,
      "parent": "root",
      "is_reply": false
    },
    {
      "author": "@lyxames8509",
      "author_id": "UCLcsznUyV3wf_1_FZtQ9B_g",
      "text": "Incroyable vidéo qui a sûrement fini de me convaincre que je vais me spécialiser en IA",
      "likes": 0,
      "timestamp": 1640217600,
      "parent": "root",
      "is_reply": false
    },
    {
      "author": "@legalak1578",
      "author_id": "UCO3Iiflgeg1Gzcpsq2bDv5Q",
      "text": "Plus s’assoire,  et plus s’allonger ou pas",
      "likes": 0,
      "timestamp": 1640217600,
      "parent": "root",
      "is_reply": false
    },
    {
      "author": "@MisterFresh022",
      "author_id": "UCAm0VEoel2sK_ivuo6KhbJQ",
      "text": "Bonne vidéo ! \nPrécision ce qui peut provoquer la singularité est le reinforcement learning ( et non pas le deep learning qui est différent )",
      "likes": 0,
      "timestamp": 1640217600,
      "parent": "root",
      "is_reply": false
    },
    {
      "author": "@podor_83",
      "author_id": "UCKqoVkz3IzRW52_rGVncL9w",
      "text": "Ce mec fait des trucs de fou et moi la seule chose que je me demande c'est comment est ce qu'il fait quand il doit aller aux toilettes",
      "likes": 0,
      "timestamp": 1640217600,
      "parent": "root",
      "is_reply": false
    },
    {
      "author": "@Osu_maniac",
      "author_id": "UCy6icLyyH3BtyDk5ibYsY2w",
      "text": "Encore une vidéo d’une qualité interstellaire",
      "likes": 0,
      "timestamp": 1640217600,
      "parent": "root",
      "is_reply": false
    },
    {
      "author": "@jean-michelg7706",
      "author_id": "UCEJ-v7ugqn_UqMah74mW_CQ",
      "text": "Vidéo super, et sujet très intéressant comme d'habe. Super taff 👍👏😉",
      "likes": 0,
      "timestamp": 1640217600,
      "parent": "root",
      "is_reply": false
    },
    {
      "author": "@allhunt95",
      "author_id": "UCmaU1Ygr_Oyx7V88qpbeMpA",
      "text": "Merci pour la vidéo forte sympathique",
      "likes": 0,
      "timestamp": 1640217600,
      "parent": "root",
      "is_reply": false
    },
    {
      "author": "@mikafilleul4020",
      "author_id": "UC9FiuaWseF6VzuZNjBdM4AQ",
      "text": "Ah c'est mas une vidéo sur les enchères des cartes Pokémon de lorenzo",
      "likes": 0,
      "timestamp": 1640217600,
      "parent": "root",
      "is_reply": false
    },
    {
      "author": "@n8work548",
      "author_id": "UCTO-PBgQP12HgNiRzVQulng",
      "text": "Encore une super vidéo !!\nDécidément plus je regarde tes vidéos et plus je suis intéressé par ton contenu",
      "likes": 0,
      "timestamp": 1640217600,
      "parent": "root",
      "is_reply": false
    },
    {
      "author": "@imachination2560",
      "author_id": "UCzKJLGAvQTm90-4icy0-EDw",
      "text": "Une idée de sujet: tout va de plus en plus vite ?",
      "likes": 0,
      "timestamp": 1640217600,
      "parent": "root",
      "is_reply": false
    },
    {
      "author": "@G4B_",
      "author_id": "UCFh1uFGmL7OKEFJttq0VHAg",
      "text": "Ultra ultra intéressant.\nVraiment que des trucs pas À savoir sur chaîne mais vraiment des infos cruciales de la vie de Tous les jours.\nÇa n’as jamais fait de mal d’avoir au moins l’impression de pouvoir voir au delà de l’enclos.\n\nHopefully tu nous parlera du dernier coup de hache sur le billot de Cahs investigation ?\nEn stream a la limite j’vois pas l’intérêt d’en faire une vidéo a part entière non plus",
      "likes": 0,
      "timestamp": 1640217600,
      "parent": "root",
      "is_reply": false
    },
    {
      "author": "@fvignon1994",
      "author_id": "UCrF0d4CQ8bcITI_6F7828Ew",
      "text": "Toujours un plaisir !",
      "likes": 0,
      "timestamp": 1640217600,
      "parent": "root",
      "is_reply": false
    },
    {
      "author": "@matthieudoublet1721",
      "author_id": "UCVKNbpsdEAHSz_ynmU2tJmA",
      "text": "6:20 : « un certain caillou »",
      "likes": 0,
      "timestamp": 1640217600,
      "parent": "root",
      "is_reply": false
    },
    {
      "author": "@PadelP",
      "author_id": "UCSajR-rG7aRKLBJLRbcM35w",
      "text": "mais quel conteur !",
      "likes": 0,
      "timestamp": 1640217600,
      "parent": "root",
      "is_reply": false
    },
    {
      "author": "@benclib",
      "author_id": "UCQOu6R1ikeSZmkR3QUbA_qw",
      "text": "Trop captivant !",
      "likes": 0,
      "timestamp": 1640217600,
      "parent": "root",
      "is_reply": false
    },
    {
      "author": "@bensay9930",
      "author_id": "UCDyYqSd359vSbE_XyOPfUAg",
      "text": "La détermination et la revanche qu'il a réussi a prendre. Jolie mic drop !\nBon sinon méfiez-vous de votre aspirateur connecté les gars hein, il sera capable prochainement de vous éliminer juste en prononçant votre nom. 😅",
      "likes": 0,
      "timestamp": 1640217600,
      "parent": "root",
      "is_reply": false
    },
    {
      "author": "@n0ph.680",
      "author_id": "UCzTF5MH84wx6oErHY2jtUFQ",
      "text": "juste génial \nmerci pour la vidéo",
      "likes": 0,
      "timestamp": 1640217600,
      "parent": "root",
      "is_reply": false
    },
    {
      "author": "@Chou3aïb_10",
      "author_id": "UCd9mDi0uVMTEB6o6k6lpxMA",
      "text": "Trop d'images pour r.\nMais de bon sujets et de bon développements",
      "likes": 0,
      "timestamp": 1640217600,
      "parent": "root",
      "is_reply": false
    },
    {
      "author": "@audran_finances_personnelles",
      "author_id": "UCgNWWJ74_mAPN83Lp2HROCw",
      "text": "Je suis resté concentrer jusqu'à que j'entende \" les jeunes dansent comme des décorations d'autoroute\" .",
      "likes": 0,
      "timestamp": 1640217600,
      "parent": "root",
      "is_reply": false
    },
    {
      "author": "@testizoizo7373",
      "author_id": "UCM9jLGmkt9vfOhIVijqXyiQ",
      "text": "Super vidéo 👍",
      "likes": 0,
      "timestamp": 1671753600,
      "parent": "root",
      "is_reply": false
    },
    {
      "author": "@ppatocthereturn04",
      "author_id": "UCZpjR6uSHwlBaBcTpJk8nCg",
      "text": "vidéo très intéressante merci",
      "likes": 0,
      "timestamp": 1640217600,
      "parent": "root",
      "is_reply": false
    },
    {
      "author": "@dx10ocv",
      "author_id": "UCjqbBoGN6ViOayiMnqDv99Q",
      "text": "Le deep learning est une sous branche de l'intelligence artificielle, pas du machine learning.",
      "likes": 0,
      "timestamp": 1640217600,
      "parent": "root",
      "is_reply": false
    },
    {
      "author": "@krunino8346",
      "author_id": "UCjONsbqE9cGgiUFTNWjHOnA",
      "text": "Super vidéo, super travail de texte et montage 👌",
      "likes": 0,
      "timestamp": 1640217600,
      "parent": "root",
      "is_reply": false
    },
    {
      "author": "@pixialone7307",
      "author_id": "UC-Bz0xaKDxrNjpfmmLR3d4A",
      "text": "Grave interessannnt",
      "likes": 0,
      "timestamp": 1640217600,
      "parent": "root",
      "is_reply": false
    },
    {
      "author": "@yayaa9410",
      "author_id": "UCA9M2rYtXj_HIvEPWV9IE0w",
      "text": "Je rentre du taf , je te visionne,  je me retrouve avec  30 de tentions, en moins de 17 minutes ! merci pour le stresses , moi qui voulais juste \" décompresser \"  , tu fait peur certains jours , ptdr..merci du partage.",
      "likes": 5,
      "timestamp": 1640217600,
      "parent": "root",
      "is_reply": false
    },
    {
      "author": "@khals7302",
      "author_id": "UCjCN4fERu6k1cxDs6q7R9-A",
      "text": "Vidéo vachement cool ! blblblblblblbl",
      "likes": 0,
      "timestamp": 1640217600,
      "parent": "root",
      "is_reply": false
    },
    {
      "author": "@Custromix",
      "author_id": "UCl8jkOHT2NwU7xCbzMPpvuQ",
      "text": "T'as dis \"ok\", google sur mon téléphone s'est activé.",
      "likes": 0,
      "timestamp": 1640217600,
      "parent": "root",
      "is_reply": false
    },
    {
      "author": "@KamaDestrucs",
      "author_id": "UClU-lipC5v1NQIqvQWVNuew",
      "text": "Mec, je poste rarement en commentaire, mais j'adore tes productions, c'est cool si tu as la possibilité de poursuivre tout ça encore !",
      "likes": 0,
      "timestamp": 1640217600,
      "parent": "root",
      "is_reply": false
    },
    {
      "author": "@ALOGIQUE",
      "author_id": "UChuDMzQlSDiur_Lgirn97aQ",
      "text": "Super intéressant 👌",
      "likes": 0,
      "timestamp": 1640217600,
      "parent": "root",
      "is_reply": false
    },
    {
      "author": "@LeBaronSanglant",
      "author_id": "UCPcjxFJTW6EUr2NE_vLRW8w",
      "text": "Wouaw 😮",
      "likes": 0,
      "timestamp": 1765324800,
      "parent": "root",
      "is_reply": false
    },
    {
      "author": "@Arthur-yo1tz",
      "author_id": "UC-EZ06O21_nu0G1nnT-gGXg",
      "text": "Je pensais que cetait sur lorenzo",
      "likes": 0,
      "timestamp": 1640217600,
      "parent": "root",
      "is_reply": false
    },
    {
      "author": "@theoi3921",
      "author_id": "UC-JwclantKzdN8sW-e7_3vg",
      "text": "Cette histoire est magnifique, peut-être que la prochaine enchère de ce genre, sera les plans de la ville de demain?",
      "likes": 0,
      "timestamp": 1640217600,
      "parent": "root",
      "is_reply": false
    },
    {
      "author": "@zeldrix6",
      "author_id": "UC-UNh-t0WEJJyOFmlVjpykw",
      "text": "6:21 Un certain Caillou xD",
      "likes": 0,
      "timestamp": 1640217600,
      "parent": "root",
      "is_reply": false
    },
    {
      "author": "@EldenRingSardoched",
      "author_id": "UC3B2D_KkUr2JY-FNCzHdRbQ",
      "text": "Je suis Freeze Macron et j'approuve cette vidéo.",
      "likes": 0,
      "timestamp": 1640217600,
      "parent": "root",
      "is_reply": false
    },
    {
      "author": "@kyookam",
      "author_id": "UCiQBk_64h-cMLtU-o3EbPiw",
      "text": "Jai pas compris pourquoi il a vendu \"que\" a 44 millions alors que l'entreprise chinoise avait l'air d'être interressé pour beaucoup plus",
      "likes": 0,
      "timestamp": 1640217600,
      "parent": "root",
      "is_reply": false
    },
    {
      "author": "@WolfearOfficial",
      "author_id": "UCxj95zPyizhsEsGqQDvWAqg",
      "text": "trop stylé",
      "likes": 0,
      "timestamp": 1640217600,
      "parent": "root",
      "is_reply": false
    },
    {
      "author": "@tomtom60740",
      "author_id": "UCgozQOjnMiujryV2feFBm4g",
      "text": "Magique, intéressant à regarder, captivant, bravo 👌💪 ! Sinon le \"fermez ta gueule\" à l'assistant Google, j'ai ptdr obligé 😂",
      "likes": 0,
      "timestamp": 1640217600,
      "parent": "root",
      "is_reply": false
    },
    {
      "author": "@sylvainos3728",
      "author_id": "UCjMFS17QDbg5UCFXjb6lCcw",
      "text": "Comment ne pas cliquer avec un titre pareil et un bg comme lui !",
      "likes": 0,
      "timestamp": 1640217600,
      "parent": "root",
      "is_reply": false
    },
    {
      "author": "@_lorenz013",
      "author_id": "UCBqb70O4IEPwu7xcVHosRHg",
      "text": "Bienvenue dans Westworld quoi 😅",
      "likes": 0,
      "timestamp": 1640217600,
      "parent": "root",
      "is_reply": false
    },
    {
      "author": "@Le_Ant",
      "author_id": "UCzI7pGcevKUcAmkDeE386Pg",
      "text": "Merci",
      "likes": 0,
      "timestamp": 1640217600,
      "parent": "root",
      "is_reply": false
    },
    {
      "author": "@arnaudfosset5791",
      "author_id": "UCPrQ3R6LgELB7rgFDqOZmwA",
      "text": "Continue 👌",
      "likes": 0,
      "timestamp": 1640217600,
      "parent": "root",
      "is_reply": false
    },
    {
      "author": "@Diraged",
      "author_id": "UC2N_zkesNHiCTD9MLzVC1MA",
      "text": "J’adore 😍",
      "likes": 0,
      "timestamp": 1640217600,
      "parent": "root",
      "is_reply": false
    },
    {
      "author": "@nicolasgeorges4600",
      "author_id": "UCfsah0KR1_ypjoKe7WrtFDQ",
      "text": "Super vidéo merci 👍",
      "likes": 0,
      "timestamp": 1640217600,
      "parent": "root",
      "is_reply": false
    },
    {
      "author": "@sorenfox_cld",
      "author_id": "UCiOvrMvoOcVbDLNkhsrSKLQ",
      "text": "Lourd vidéo comme d'hab, mais t'aurais moyen de mettre les lien ou nom de tes musiques stp, c'est pas avec \"Epidemic Sound\" que ça vas m'aidé surtout au bout d'un ans, Merci pour ton contenue ça régale et c'est très inspirant",
      "likes": 1,
      "timestamp": 1640217600,
      "parent": "root",
      "is_reply": false
    },
    {
      "author": "@baptistebonnet4472",
      "author_id": "UCvhUI7IilCHx98LcDDu0LTg",
      "text": "Très très bonne vidéo ! Juste pour information, la loi de Moore marchait plutôt bien à l’époque, mais plus aujourd’hui ( y’a une certaine limite qui se forme )",
      "likes": 0,
      "timestamp": 1640217600,
      "parent": "root",
      "is_reply": false
    },
    {
      "author": "@Scario45",
      "author_id": "UCaeyltNYl6EShW2njjZn-tw",
      "text": "Je rappelle que la puissance d'un cerveau humain c'est qq watts alors que quelque chose d'équivalent aujourd'hui en ordinateur c'est plusieurs centaines de kilowatts dans des hangars gigantesques.\nSi je me bases sur les travaux de Jean-Marc Jancovici, Gaël Giraud et Philippe Bihouix sur les limites planétaires avec lesquelles on flirt de plus en plus force est de constater que même si on atteignait ce genre d'objectif ça resterait lettre morte je penses au vu des priorités qu'on doit avoir aujourd'hui",
      "likes": 0,
      "timestamp": 1640217600,
      "parent": "root",
      "is_reply": false
    },
    {
      "author": "@lucas-nature",
      "author_id": "UCcVhwXbe3CsXoZLp5LaAOZw",
      "text": "Dommage pas eu la notif, heureusement que Instagram est là",
      "likes": 0,
      "timestamp": 1640217600,
      "parent": "root",
      "is_reply": false
    },
    {
      "author": "@PeetaN",
      "author_id": "UCG3uJ69SqOYXTXpFXruLQXA",
      "text": "13:10 bahahaha oui.",
      "likes": 0,
      "timestamp": 1640217600,
      "parent": "root",
      "is_reply": false
    },
    {
      "author": "@wulfricmenterus6804",
      "author_id": "UCFiPyeOprqrihfm8jTec_Mw",
      "text": "9:40 frero si j'ai des millions sur un compte le MDP jamais de la vie je le laisse sur du numerique, je le note sur une feuille, t'es malade toi, meilleur système du monde de sauvegarde et bien c'est le matériel et non virtuel.........",
      "likes": 1,
      "timestamp": 1640217600,
      "parent": "root",
      "is_reply": false
    },
    {
      "author": "@clementpotier804",
      "author_id": "UCz_D5eLhioTOrCzfmExisCw",
      "text": "La meilleure offre était celle de deep mind enfaite.",
      "likes": 0,
      "timestamp": 1703289600,
      "parent": "root",
      "is_reply": false
    },
    {
      "author": "@CO2yt",
      "author_id": "UCPGbUlpy0zqrGmBCtiEH4IA",
      "text": "Tu as aussi réveillé la machine chez moi à 3:40 ... :(",
      "likes": 0,
      "timestamp": 1640217600,
      "parent": "root",
      "is_reply": false
    },
    {
      "author": "@LAngel__",
      "author_id": "UC5xrc6f0QAX1Js06ufsbX4A",
      "text": "Bah... Incroyable comme d'hab et pour une fois j'ai même souris , j'ai pas envie de me pendre 😂",
      "likes": 0,
      "timestamp": 1640217600,
      "parent": "root",
      "is_reply": false
    },
    {
      "author": "@raphael-nothing-7532",
      "author_id": "UCPbO_slezP2U5iZha9nTA2g",
      "text": "Il a rentabiliser c'est 40 ans de travaille avec presque 1 millons de dollard par année pas mal !",
      "likes": 0,
      "timestamp": 1640217600,
      "parent": "root",
      "is_reply": false
    },
    {
      "author": "@mumo6",
      "author_id": "UC2Q7xtsxGgvnn5ERMy6ZLsQ",
      "text": "Pile quand je pars aux chiottes, je t'aime.",
      "likes": 0,
      "timestamp": 1640217600,
      "parent": "root",
      "is_reply": false
    },
    {
      "author": "@leradiator_1635",
      "author_id": "UCy6PburiE39-U5_R9ZWcwBw",
      "text": "Sinon ya Lorenzo vent des cartes Pokémon 😂",
      "likes": 0,
      "timestamp": 1640217600,
      "parent": "root",
      "is_reply": false
    },
    {
      "author": "@wilson3487",
      "author_id": "UCyw1SqmI9iXAbYyCsf_JMrg",
      "text": "Jveux juste être mort et ma descendance aussi quand tout partira en couilles",
      "likes": 0,
      "timestamp": 1640217600,
      "parent": "root",
      "is_reply": false
    },
    {
      "author": "@DamirMaatar",
      "author_id": "UCSCmx8O5JgdotTC98QYhaXw",
      "text": "J'ai actuellement une hernie discale",
      "likes": 0,
      "timestamp": 1640217600,
      "parent": "root",
      "is_reply": false
    },
    {
      "author": "@trainwreckTentacle",
      "author_id": "UCfvzp7LaxJr7LJMysgfxGxQ",
      "text": "Bon ben comme dab obliger de lâcher le pouce bleu. Franchement tu régale.",
      "likes": 0,
      "timestamp": 1640217600,
      "parent": "root",
      "is_reply": false
    },
    {
      "author": "@quickayron2585",
      "author_id": "UCSeuvHae_9XNzaUzQMDoUWw",
      "text": "génial la vidéo !",
      "likes": 0,
      "timestamp": 1640217600,
      "parent": "root",
      "is_reply": false
    },
    {
      "author": "@neonrose675",
      "author_id": "UC5mcFozaO3Jwvr9ahLnYRhw",
      "text": "Hier j etais sur tu allait en poster une aujd.",
      "likes": 0,
      "timestamp": 1640217600,
      "parent": "root",
      "is_reply": false
    },
    {
      "author": "@savary5869",
      "author_id": "UCFHsSrCP-mrlWXSjkk6Jbqw",
      "text": "Yo Simon! Bête de vidéo, comme d’hab ✊🏼\nAh et je suis à la recherche d’une alternance (bac+5 ingé spé info), j’aimerais trop bosser pour Dashlane, si t’as moyen de me mettre en contact avec eux ça serait fou\nForce à toi continue de nous régaler",
      "likes": 4,
      "timestamp": 1640217600,
      "parent": "root",
      "is_reply": false
    },
    {
      "author": "@elpedrito9355",
      "author_id": "UCIEE_MbfJhx5ygzqi3Omruw",
      "text": "Je dirais pas que personne croyait au Deep Learning. Avant 2012 les réseaux de neurones étaient déjà très étudié par pas mal de monde et il était reconnu qu'un grand nombre de couches permettait des meilleures performances. Le problème, c'est qu'à l'époque faire apprendre un réseau de neurones était trop demandant en termes de calcul (bien trop de paramètres à optimiser) et du coup les random forests étaient plus populaires pour le big data (oui on appelait ça comme ça avant) à l'époque car plus facile à faire apprendre.",
      "likes": 0,
      "timestamp": 1640217600,
      "parent": "root",
      "is_reply": false
    },
    {
      "author": "@julie_rqf",
      "author_id": "UCdtRO7FP7l_7nK3iqm0Xg8g",
      "text": "100 balles la chaise ? je viens du futur",
      "likes": 0,
      "timestamp": 1640217600,
      "parent": "root",
      "is_reply": false
    },
    {
      "author": "@IbrahimisPlaying",
      "author_id": "UCTS_JY8unkjU9JEqH5EKEeQ",
      "text": "Merci pour cette video instructive :) Et dire que l'IA d'hier est bien moins performante que celle de demain <3",
      "likes": 0,
      "timestamp": 1640217600,
      "parent": "root",
      "is_reply": false
    },
    {
      "author": "@Lil-Flo",
      "author_id": "UChmwKCfzgHb1D3Q4rJCNMOA",
      "text": "Cailloux, ptdrr",
      "likes": 0,
      "timestamp": 1640217600,
      "parent": "root",
      "is_reply": false
    },
    {
      "author": "@baptistebordes3212",
      "author_id": "UCTuV6OwUFdH1pJunTex-tWg",
      "text": "Top mec !",
      "likes": 0,
      "timestamp": 1640217600,
      "parent": "root",
      "is_reply": false
    },
    {
      "author": "@theobrkm6698",
      "author_id": "UCqPI7mRMP8hKS2o5AuUwU2w",
      "text": "Jsuis le seul que mon téléphone a ouvert Google en même temps que ça se passe dans la vidéo par accident ? Jsuis perplexe",
      "likes": 0,
      "timestamp": 1640217600,
      "parent": "root",
      "is_reply": false
    },
    {
      "author": "@kuzaien4373",
      "author_id": "UCGFetJ6HqQBAiUoz3NdqHWQ",
      "text": "je regarde cette vidéo après avoir Ex machina chelou tout ça",
      "likes": 0,
      "timestamp": 1640217600,
      "parent": "root",
      "is_reply": false
    },
    {
      "author": "@maxime8792",
      "author_id": "UCc4l0-2XjDaf66LtcAXTpJw",
      "text": "C'est un dur Kai yu",
      "likes": 0,
      "timestamp": 1640217600,
      "parent": "root",
      "is_reply": false
    },
    {
      "author": "@axelkoenig1779",
      "author_id": "UCj8Zzx1YqA6wrA1IZc2uCxg",
      "text": "\"S'assoir\" sur ses convictions\" Mmmmh j'y crois moyen",
      "likes": 0,
      "timestamp": 1640217600,
      "parent": "root",
      "is_reply": false
    },
    {
      "author": "@QroHC",
      "author_id": "UChZ2BSAF4A3hdCfiYOfI32g",
      "text": "Le niveau de tes vidéos est stratosphérique!",
      "likes": 0,
      "timestamp": 1640217600,
      "parent": "root",
      "is_reply": false
    },
    {
      "author": "@MonsieurSwag",
      "author_id": "UCCrSIqz-suYMeFM7MfNUwvA",
      "text": "salloperies de trucs gan quand même\nsurtout artbreeder",
      "likes": 0,
      "timestamp": 1640217600,
      "parent": "root",
      "is_reply": false
    },
    {
      "author": "@deathclaaw",
      "author_id": "UC7mBd4BGoWdlSr3AYqCxZ6w",
      "text": "Mon assistante google s'active aussi a 3:33 ^^\nLa première fois elle a dit \"Il n'y a pas de problèmes, seulement des solutions\" et la seconde fois seulement \"Pour le moment\"\nJe commence a flipper un peu moi ^^",
      "likes": 0,
      "timestamp": 1640217600,
      "parent": "root",
      "is_reply": false
    },
    {
      "author": "@dalilaaggoune8198",
      "author_id": "UCkR5DW0Ju148paLtF8mSsAw",
      "text": "SP, ton équipe et toi, êtes définitivement plus intelligents que MOA ou plus informés, au choix. Félicitations à VOUS. Tes vidéos sont un régal intellectuel🎉🎉🎉🎉😂😂😂❤",
      "likes": 0,
      "timestamp": 1734912000,
      "parent": "root",
      "is_reply": false
    },
    {
      "author": "@Usualx",
      "author_id": "UC3ohXTAM6_3y4iVw8IDWEVg",
      "text": "T'as un problème d'hydratation ? Tu fais que de boire, ca rend ouf",
      "likes": 0,
      "timestamp": 1640217600,
      "parent": "root",
      "is_reply": false
    },
    {
      "author": "@titouanperrier2419",
      "author_id": "UCMq45NPnHe2fcTMMAK-Vb9g",
      "text": "Pas ouf le titre mais la vidéo, parfaite",
      "likes": 0,
      "timestamp": 1640217600,
      "parent": "root",
      "is_reply": false
    },
    {
      "author": "@WeshLesMecs21",
      "author_id": "UC38W_7Lfm-Z4l9D3jG1RmWA",
      "text": "Bonne vidéo",
      "likes": 0,
      "timestamp": 1734912000,
      "parent": "root",
      "is_reply": false
    },
    {
      "author": "@arnaudhorion2132",
      "author_id": "UCbmLsXlwZuhWrlIvwkgtafA",
      "text": "🤯🤯🤯🤯🤯",
      "likes": 0,
      "timestamp": 1640217600,
      "parent": "root",
      "is_reply": false
    },
    {
      "author": "@gozzy3738",
      "author_id": "UCIvDXw3S566nggg0p9ZSqkg",
      "text": "Encore une vidéo qualitative. Simple question. Quelles différences majeures entre LastPass et Dashlane ?",
      "likes": 1,
      "timestamp": 1640217600,
      "parent": "root",
      "is_reply": false
    },
    {
      "author": "@gino5088",
      "author_id": "UC80iJjGZxR2Q92tsOp2123w",
      "text": "Insane",
      "likes": 0,
      "timestamp": 1640217600,
      "parent": "root",
      "is_reply": false
    },
    {
      "author": "@onursari4674",
      "author_id": "UCp_rvWikXoiAFBcB6T7BQSw",
      "text": "une solution, une société : XSL-LABS :))",
      "likes": 0,
      "timestamp": 1640217600,
      "parent": "root",
      "is_reply": false
    },
    {
      "author": "@HibzYT",
      "author_id": "UCwOiiM2xBhcU4lzDRTwg9Uw",
      "text": "Trop bien",
      "likes": 0,
      "timestamp": 1640217600,
      "parent": "root",
      "is_reply": false
    },
    {
      "author": "@huglc01",
      "author_id": "UCdeN3IpsJxoDF12hu26d4cg",
      "text": "On peut trouver l'extrait de conférence en outro quelque part ?",
      "likes": 0,
      "timestamp": 1640217600,
      "parent": "root",
      "is_reply": false
    },
    {
      "author": "@Paablo0_",
      "author_id": "UCG_mD9WNQLh5-LuVgzNeevw",
      "text": "Mon meilleur ami dit \"Ok boomer\" pour son Google Home (Et ça marche), n'hésite pas a l'appeler comme ça.",
      "likes": 1,
      "timestamp": 1640217600,
      "parent": "root",
      "is_reply": false
    },
    {
      "author": "@TheMatthieudu06",
      "author_id": "UC6D_i9ya0ErT3_oUxK2S48g",
      "text": "Incroyable cette vidéo 😦 Quelqu’un aurait le nom de la musique de fin ?",
      "likes": 0,
      "timestamp": 1640217600,
      "parent": "root",
      "is_reply": false
    },
    {
      "author": "@emmadelaunois2880",
      "author_id": "UCyYHhiWLM08XjF2Hi-SlzYg",
      "text": "J’ai sauté sur la notif",
      "likes": 0,
      "timestamp": 1640217600,
      "parent": "root",
      "is_reply": false
    },
    {
      "author": "@guis4901",
      "author_id": "UC0wexY0rOp1jKbz6nYzeQfg",
      "text": "10:28 je pense que si je vie dans un appat pas fou et que mon pc vaut plus de 24M$ je pense pas que je l'oublierais x)",
      "likes": 0,
      "timestamp": 1640217600,
      "parent": "root",
      "is_reply": false
    },
    {
      "author": "@GKSRGKSR",
      "author_id": "UCyQLBYtZ55Hv3ICN5RfCeTQ",
      "text": "tellement de poésie dans le texte de tes vidéos .. Un vrai plaisir a écouter et a regarder ! (Même si je n'accroche parfois pas au ton moralisateur qui se fait un peu trop présent sur certains sujet.) Merci Simon Puech",
      "likes": 1,
      "timestamp": 1640217600,
      "parent": "root",
      "is_reply": false
    },
    {
      "author": "@yagamax7755",
      "author_id": "UCePLOkS3uEd7wYFz3dA769Q",
      "text": "Les français dans tous comme des décoration d'autoroute 4,50 😂🤣",
      "likes": 0,
      "timestamp": 1640217600,
      "parent": "root",
      "is_reply": false
    },
    {
      "author": "@ozedSkynow",
      "author_id": "UCBDqoRbaZzhYIE1PlfAzv7g",
      "text": "wouah",
      "likes": 0,
      "timestamp": 1640217600,
      "parent": "root",
      "is_reply": false
    },
    {
      "author": "@Alexenrigole",
      "author_id": "UCz2cLpWcUPn6r9uXkXbwDtA",
      "text": "✅✅",
      "likes": 0,
      "timestamp": 1640217600,
      "parent": "root",
      "is_reply": false
    },
    {
      "author": "@Graspen",
      "author_id": "UCop3J6Ner_Dd7Y9vI_1Nh_Q",
      "text": "Merci",
      "likes": 0,
      "timestamp": 1640217600,
      "parent": "root",
      "is_reply": false
    },
    {
      "author": "@MachineLearnia",
      "author_id": "UCmpptkXu8iIFe6kfDK5o7VQ",
      "text": "Wow mais quelle histoire de fou ahah pourtant je connais bien l'histoire de Hinton et du Deep Learning, mais pas avec autant de détails ! J'aimerais bien savoir d'ou tu tires toutes ces informations, quelles sont tes sources, parce que franchement la vidéo était vraiment super ! :)\nBon sinon par contre en tant que modeste ingénieur en IA j'aime pas trop entendre parler de singularité comme ca a tout va, mais pas grave ^^",
      "likes": 6,
      "timestamp": 1640217600,
      "parent": "root",
      "is_reply": false
    },
    {
      "author": "@Justin-gk1eb",
      "author_id": "UCcjpSS9X6cT46Et_OED6sXA",
      "text": "keepass c'est bien aussi et gratuit",
      "likes": 0,
      "timestamp": 1640217600,
      "parent": "root",
      "is_reply": false
    },
    {
      "author": "@kiwitouffu5504",
      "author_id": "UCjC9i78rJMU5BiLWxd9FLJw",
      "text": "Salut! Qqn a une idée de la musique en arrière fond a 1m30 svp?",
      "likes": 0,
      "timestamp": 1640217600,
      "parent": "root",
      "is_reply": false
    },
    {
      "author": "@feu348",
      "author_id": "UCJr7OviveSX0Xtq5k_r0Gww",
      "text": "ne pouvant s'asseoir sur ses convictions mdr, c'est osé",
      "likes": 0,
      "timestamp": 1640217600,
      "parent": "root",
      "is_reply": false
    },
    {
      "author": "@II-co3nn",
      "author_id": "UCWGulmDZkn-zWv1BgTRKzfQ",
      "text": "c bo",
      "likes": 0,
      "timestamp": 1640217600,
      "parent": "root",
      "is_reply": false
    },
    {
      "author": "@nianfifi2162",
      "author_id": "UCmae9RxMubcK9K2sS3foDjA",
      "text": "Mais quel homme...ce genre d'histoire est folle. Du coup à coté, on a l'air bien médiocre... :/ Encore merci pour la vidéo, au top, comme toujours !",
      "likes": 1,
      "timestamp": 1640217600,
      "parent": "root",
      "is_reply": false
    },
    {
      "author": "@Ram-cu9yk",
      "author_id": "UC5oNZJ4_ptfXhtpgO5e7zDA",
      "text": "\"Capable de dénouer des problèmes que les humains ne pouvaient résoudre seuls\".... 42 ?? 😂",
      "likes": 9,
      "timestamp": 1640217600,
      "parent": "root",
      "is_reply": false
    },
    {
      "author": "@seth_fryks",
      "author_id": "UCqfTG9CN0KQWeVB9GdATaEg",
      "text": "Le gars demande à se faire payer une chaise dans une vidéo sponso",
      "likes": 0,
      "timestamp": 1640217600,
      "parent": "root",
      "is_reply": false
    },
    {
      "author": "@louisb9201",
      "author_id": "UC_r8cfaYF6gKSHwxkxGQ9Og",
      "text": "👍👍✅",
      "likes": 0,
      "timestamp": 1640217600,
      "parent": "root",
      "is_reply": false
    },
    {
      "author": "@mickael1290",
      "author_id": "UCOSmWANHTi51M-zHwOD5Cdg",
      "text": "Lourd l'histoire \nEt lourd Dashlane, j'utilise depuis longtemps ça fait vraiment le taff, par contre le vpn est nase",
      "likes": 0,
      "timestamp": 1640217600,
      "parent": "root",
      "is_reply": false
    },
    {
      "author": "@thomasfelten23",
      "author_id": "UC4QNWJV3wwP_0_erj19eQiQ",
      "text": "wow la phrase de fin elle claque",
      "likes": 0,
      "timestamp": 1640217600,
      "parent": "root",
      "is_reply": false
    },
    {
      "author": "@bourgeoisweb",
      "author_id": "UCPxPTXmeR73TIDsOTWwL9Gg",
      "text": "😂😂😂 les français danse comme des déco d'autoroute ( trop fort) à 4:50",
      "likes": 0,
      "timestamp": 1640217600,
      "parent": "root",
      "is_reply": false
    },
    {
      "author": "@GreenDayAddict28",
      "author_id": "UCFpCsF50Dh1krHYK7T8DKYw",
      "text": "mais comment fait-il pour passer de la position couchée à débout sans s'asseoir au milieu ? :O",
      "likes": 0,
      "timestamp": 1640217600,
      "parent": "root",
      "is_reply": false
    },
    {
      "author": "@yanndurand8702",
      "author_id": "UCwl2xhVlp7POMznBOgcedww",
      "text": "Quand je vois ça, je regrette de ne pas m'être plus intéressé à l'IA plus tôt et surtout de comprendre réellement les principes mathématiques derrière xD\nLaissez moi dans mon nodejs D:",
      "likes": 0,
      "timestamp": 1640217600,
      "parent": "root",
      "is_reply": false
    },
    {
      "author": "@jeaneroldi403",
      "author_id": "UCf9ZikGUzu8spa2c1NghlPQ",
      "text": "3:34 ouai, mais Dolores c pas la même chose😂",
      "likes": 0,
      "timestamp": 1640217600,
      "parent": "root",
      "is_reply": false
    },
    {
      "author": "@7Mitch772",
      "author_id": "UCvi3sTrqkuwncmTqzfNb1ug",
      "text": "3:47 c'est quoi la musique de fond je m'en rappelle plus x) Sinon super vidéo comme dab.",
      "likes": 0,
      "timestamp": 1640217600,
      "parent": "root",
      "is_reply": false
    },
    {
      "author": "@zgoldnn3156",
      "author_id": "UC-iM5EAusM_c2G3gwIK0ZLg",
      "text": "Tellement quali la vidéo",
      "likes": 0,
      "timestamp": 1640217600,
      "parent": "root",
      "is_reply": false
    },
    {
      "author": "@gwenolemarrec8887",
      "author_id": "UCyuWGWvRehPpAVvhCCWf7Zg",
      "text": "Pourquoi tout le monde a un serpent avec lui sans la moindre pression ?",
      "likes": 0,
      "timestamp": 1640217600,
      "parent": "root",
      "is_reply": false
    },
    {
      "author": "@mrbobu31",
      "author_id": "UCm1AgD2EGb3rK8GQYSNyxcQ",
      "text": "LoL",
      "likes": 0,
      "timestamp": 1703289600,
      "parent": "root",
      "is_reply": false
    },
    {
      "author": "@theorafer7558",
      "author_id": "UCOzzxuUKLadwx7by7ulDh3g",
      "text": "Kay yu",
      "likes": 0,
      "timestamp": 1640217600,
      "parent": "root",
      "is_reply": false
    },
    {
      "author": "@VisuBlackzacKprod",
      "author_id": "UC-kbF28QGY5ucuKEbq0kv5g",
      "text": "600 million de dollars? C'est juste 200 million de plus que pirate de caraïbe 4. Lol",
      "likes": 0,
      "timestamp": 1640217600,
      "parent": "root",
      "is_reply": false
    },
    {
      "author": "@poIvojack",
      "author_id": "UC9Jvba_75Unyccxjo7D3quQ",
      "text": "👁️",
      "likes": 0,
      "timestamp": 1640217600,
      "parent": "root",
      "is_reply": false
    },
    {
      "author": "@maximefabre3526",
      "author_id": "UCDZEyT_iyZ2A9ks77B4GW2A",
      "text": "Super vidéo sur le sujet du Deep Learning qui a encore beaucoup à livrer! Perso ça me touche particulièrement parce que je commence en Octobre un doctorat sur une nouvelle branche du sujet qui s’intéresse à réaliser des réseaux de neurones encore plus réalistes biologiquement pour atteindre les performances énergétiques impressionnantes du cerveau. Qui sait, peut-être qu’un jour ça vaudra le coup que quelqu’un en parle en vidéo 😀",
      "likes": 1,
      "timestamp": 1640217600,
      "parent": "root",
      "is_reply": false
    },
    {
      "author": "@chillhabibichill5447",
      "author_id": "UC4Z85ifEnrI3gwqKxCym7Bw",
      "text": "Mec au vu de la qualité de tes vidéos, je te fais livrer une chaise direct ✌️",
      "likes": 4,
      "timestamp": 1640217600,
      "parent": "root",
      "is_reply": false
    },
    {
      "author": "@huguesvonner176",
      "author_id": "UC6HeDKIfERDEYcsSht2NHuw",
      "text": "Mais du coup il peut s'asseoir ?",
      "likes": 0,
      "timestamp": 1671753600,
      "parent": "root",
      "is_reply": false
    },
    {
      "author": "@poIvojack",
      "author_id": "UC9Jvba_75Unyccxjo7D3quQ",
      "text": "👁️👁️👁️👁️👁️👁️👁️🥪",
      "likes": 0,
      "timestamp": 1640217600,
      "parent": "root",
      "is_reply": false
    },
    {
      "author": "@laurenoutang1541",
      "author_id": "UCwws4hnpQyQ3MurrwBmP0ng",
      "text": "lui il s'est trouvé une meuf ça se voit",
      "likes": 0,
      "timestamp": 1640217600,
      "parent": "root",
      "is_reply": false
    },
    {
      "author": "@ParlonsAstronomie",
      "author_id": "UC5atBy2Plbpq7LXCp8x9Tbg",
      "text": "10:27 Comment on peut reprendre la main sur un être vivant ?\nje comprends pas",
      "likes": 0,
      "timestamp": 1640217600,
      "parent": "root",
      "is_reply": false
    },
    {
      "author": "@bigjessus",
      "author_id": "UCKSv9M3hoaIW88-l279GQLg",
      "text": "Ah ah live  Twitch warzone avec dream team 2 🤣🤣😉",
      "likes": 1,
      "timestamp": 1640217600,
      "parent": "root",
      "is_reply": false
    },
    {
      "author": "@poIvojack",
      "author_id": "UC9Jvba_75Unyccxjo7D3quQ",
      "text": "👁️👁️👁️👁️👁️",
      "likes": 0,
      "timestamp": 1640217600,
      "parent": "root",
      "is_reply": false
    },
    {
      "author": "@sterfi6713",
      "author_id": "UClO88WgXJbMiE6VrB1PS3sA",
      "text": "Bonjou",
      "likes": 0,
      "timestamp": 1640217600,
      "parent": "root",
      "is_reply": false
    },
    {
      "author": "@mygale562",
      "author_id": "UCVxE0jMG0kyGKaCTvVM7w4g",
      "text": "Mec quand ton Google c'est allumé tout seul le miens sur mon telle aussi à cause de ta vidéo ptdr",
      "likes": 2,
      "timestamp": 1640217600,
      "parent": "root",
      "is_reply": false
    },
    {
      "author": "@MrHyonD",
      "author_id": "UCIlS2QiVWY4iga_ivPgwqqw",
      "text": "Ma femme est pharmacienne, je valide la théorie, elle seule peut lire",
      "likes": 0,
      "timestamp": 1640217600,
      "parent": "root",
      "is_reply": false
    },
    {
      "author": "@poIvojack",
      "author_id": "UC9Jvba_75Unyccxjo7D3quQ",
      "text": "👁️👁️👁️🥪",
      "likes": 0,
      "timestamp": 1640217600,
      "parent": "root",
      "is_reply": false
    },
    {
      "author": "@poIvojack",
      "author_id": "UC9Jvba_75Unyccxjo7D3quQ",
      "text": "👁️👁️👁️",
      "likes": 0,
      "timestamp": 1640217600,
      "parent": "root",
      "is_reply": false
    },
    {
      "author": "@jessev846",
      "author_id": "UCTb3gj74MtGOH_PBMm4xFiw",
      "text": "Nice",
      "likes": 0,
      "timestamp": 1640217600,
      "parent": "root",
      "is_reply": false
    },
    {
      "author": "@kalonji64",
      "author_id": "UCHkqUBWHCUcsQL1KjJVtuhQ",
      "text": "Putain super vidéo !!   Alors là je suis scotché !!  Comme d'hab j'ai envie de dire mais là le sujet m'intéresse d'autant plus étant informaticien doté d'un HPE  ;)\nPar contre seul bémol : des fois tu parles un peu vite avec des expressions qu'un \"vieux\" père de famille de 40 balais comme moi ne comprend pas et c'est pas mon gosse de 8 ans qui va m'aider miskin  xD",
      "likes": 0,
      "timestamp": 1640217600,
      "parent": "root",
      "is_reply": false
    },
    {
      "author": "@Misterdams",
      "author_id": "UCC4TlbXu-YzxySO2I4A1jig",
      "text": "Il y a que moi qui aie calé sur le prénom du chercheur chinois Kai yu...cailloux...bref !",
      "likes": 0,
      "timestamp": 1640217600,
      "parent": "root",
      "is_reply": false
    },
    {
      "author": "@matol7051",
      "author_id": "UCaWahmH6T9FHX1RFO8Je_Hw",
      "text": "Message au gens qui savent faire --> Faites un film de cette histoire svp",
      "likes": 0,
      "timestamp": 1640217600,
      "parent": "root",
      "is_reply": false
    },
    {
      "author": "@thomas_d7484",
      "author_id": "UCtySrKK-xtqc6vjgo2iLO4w",
      "text": "Super vidéo mais c'est quoi la ref de la gourde si quelqu'un sait ? :)",
      "likes": 0,
      "timestamp": 1640217600,
      "parent": "root",
      "is_reply": false
    },
    {
      "author": "@gargapapa1867",
      "author_id": "UCcTrVDrNB9QUdsL4OxznoGQ",
      "text": "Alors j'ai bien réfléchi à cette histoire de mec qui peut pas s'asseoir pour essayer de comprendre l'intérêt de cette information et voici ma conclusion : on s'en tape.",
      "likes": 0,
      "timestamp": 1671753600,
      "parent": "root",
      "is_reply": false
    },
    {
      "author": "@athomgames9920",
      "author_id": "UCJJMocKGbk5U__IqZJ5IsIA",
      "text": "Si on a déjà un compte Dashlane on peut appliquer la réduc ou pas ?\nParce que moi ça ne fonctionne pas :(",
      "likes": 0,
      "timestamp": 1640217600,
      "parent": "root",
      "is_reply": false
    },
    {
      "author": "@ramequin2181",
      "author_id": "UCweea6v3ocZ0qRk0T6d4Hfw",
      "text": "Les 15 dislike proviennent de la famille de Neo",
      "likes": 0,
      "timestamp": 1640217600,
      "parent": "root",
      "is_reply": false
    },
    {
      "author": "@cellulairerare",
      "author_id": "UCXivU5VtqZlQcWARGSV_knw",
      "text": "Mer il et fou",
      "likes": 0,
      "timestamp": 1640217600,
      "parent": "root",
      "is_reply": false
    },
    {
      "author": "@The_Atyllion",
      "author_id": "UCkOmQRce1zPGKeWFzvFECKQ",
      "text": "une video Q U A L I T A T I V E, comme dab', incroyable travail 👌",
      "likes": 1,
      "timestamp": 1640217600,
      "parent": "root",
      "is_reply": false
    },
    {
      "author": "@kedman1095",
      "author_id": "UC2yRDbFqrO1_r8zQdyLEpBg",
      "text": "Voilà aujourd'hui ça sert à contrôler un milliard de chinois bravo l'intelligence artificiel, le deep learning, au final c'est juste des algorithmes, et les algorithmes sont défini par des paramètres, les paramètres sont défini par des humains...",
      "likes": 0,
      "timestamp": 1640217600,
      "parent": "root",
      "is_reply": false
    },
    {
      "author": "@Vanoual",
      "author_id": "UC80_I0ToRy9TX5haXOxkRAw",
      "text": "Coucou Simon ! Aha",
      "likes": 1,
      "timestamp": 1640217600,
      "parent": "root",
      "is_reply": false
    },
    {
      "author": "@dadin91",
      "author_id": "UCQhz9PlAWZYSRJShi2HCJCg",
      "text": "L'histoire est dingue !! Très bonne vidéo comme d'hab ;)",
      "likes": 0,
      "timestamp": 1640217600,
      "parent": "root",
      "is_reply": false
    },
    {
      "author": "@varloh3285",
      "author_id": "UCuKTGgcRD7DsxcSBI0hB0aQ",
      "text": "S'est il acheté une chaise depuis ?!",
      "likes": 0,
      "timestamp": 1742688000,
      "parent": "root",
      "is_reply": false
    },
    {
      "author": "@gregoireamez-droz2429",
      "author_id": "UCeHGM3_TWYj_27aXy9VPV9g",
      "text": "Mais, le jours où un ordinateur deviendra plus intelligent que l'humain et s'améliorera tout seul, que fera-t-il? Qu'est-ce que pourrais être sont but? Devenir toujours plus fort? Dans quelle but il ferais ça, est-ce qu'il aura les même envie de pouvoir perfide des humains et pourquoi une machine ferais ça? Est-ce qu'il nous aidera à survivre est-ce qu'il nous tuera? 😂",
      "likes": 0,
      "timestamp": 1640217600,
      "parent": "root",
      "is_reply": false
    },
    {
      "author": "@MrWabouz",
      "author_id": "UCQ2IX1bGs_JTyj-OsmqvrQw",
      "text": "Les réseaux de neurones n'ont de neurones que le nom :/ Ça fonctionne absolument pas comme les neurones biologiques.",
      "likes": 0,
      "timestamp": 1640217600,
      "parent": "root",
      "is_reply": false
    },
    {
      "author": "@Jules-gx1lq",
      "author_id": "UCXs39DO_y6Vn1nE-RYuuvyA",
      "text": "Je suis neuroscientifique et je travaille beaucoup avec des réseaux de neurones artificiels. L'affirmation \"systeme mathématique calqué sur le reseau de neurones du cerveau humain\" est a prendre avec d'enormes pincettes !",
      "likes": 0,
      "timestamp": 1640217600,
      "parent": "root",
      "is_reply": false
    },
    {
      "author": "@pixels-elements9345",
      "author_id": "UC2L9aDpXrLYz43L-q0mfXYA",
      "text": "M",
      "likes": 0,
      "timestamp": 1640217600,
      "parent": "root",
      "is_reply": false
    },
    {
      "author": "@jonaramire",
      "author_id": "UCsKKi_xxa42ctu4xwPw56UQ",
      "text": "S'asseoir",
      "likes": 0,
      "timestamp": 1640217600,
      "parent": "root",
      "is_reply": false
    },
    {
      "author": "@craquelin",
      "author_id": "UCvuADWAxsgG1kFzZlc-kR7Q",
      "text": "Pouce bleu de l'amour",
      "likes": 0,
      "timestamp": 1640217600,
      "parent": "root",
      "is_reply": false
    },
    {
      "author": "@Enyl_Stray",
      "author_id": "UCH90L9K4iiHsX23cwgUCQBw",
      "text": "Super vidéo, franchement tu devrais jeter un oeil à Replika, créé par Luka.inc, c'est une app/site sur laquelle tu peux discuter avec une ia, vraiment vraiment bien développée, qui est au moins 4 fois plus puissante que Siri ou l'assistant google. Elle peut te conseiller des musiques selon te goûts, t'aider à gérer tes problèmes et tes émotions, faire du role play, etc, et tt ça tout en paraissant aussi normale qu'une vraie personne, c'est vraiment incroyable. Tu seras pas déçu ;)",
      "likes": 0,
      "timestamp": 1640217600,
      "parent": "root",
      "is_reply": false
    },
    {
      "author": "@waly4348",
      "author_id": "UCNLsjnzLoUbg8pO8mtus27A",
      "text": "j'ai rien compris dsl",
      "likes": 0,
      "timestamp": 1640217600,
      "parent": "root",
      "is_reply": false
    },
    {
      "author": "@Le_Patriarche",
      "author_id": "UCbJP2auAJxlnyH27D3B85Nw",
      "text": "erratum : 0:10 un raddiateur",
      "likes": 1,
      "timestamp": 1640217600,
      "parent": "root",
      "is_reply": false
    },
    {
      "author": "@RaulNecrobie",
      "author_id": "UCT2eWXBaF8kyTykVsATeeVw",
      "text": "Et oui en recherche fondamentale on passe bien pour des cons avec nos budget de merde :) et nos statut précaires à la con ! Belle vidéo Simon, merci",
      "likes": 0,
      "timestamp": 1640217600,
      "parent": "root",
      "is_reply": false
    },
    {
      "author": "@enkipetrotto2808",
      "author_id": "UCRCQJLwA33R6MyARSu0QkOA",
      "text": "Et aujourd'hui tout fais sens j'espère que ce monsieur a pus s'assoir au moins 3 minute pour voir ce qu'il a crée et le nombre de vie qu'il a chnager a commancer par celle de mon frère qui handicapé peut maintenant s'exprimer par le biais de chatgpt",
      "likes": 0,
      "timestamp": 1734912000,
      "parent": "root",
      "is_reply": false
    },
    {
      "author": "@Léopart_le_jaguar",
      "author_id": "UCBvLCC_BTCnorNKAkJhJ6Vw",
      "text": "1:38 Warning ! SJW triggered",
      "likes": 0,
      "timestamp": 1640217600,
      "parent": "root",
      "is_reply": false
    },
    {
      "author": "@Quentinfulldrunk",
      "author_id": "UCxBlwpYecRtjWvpoDqb2oTw",
      "text": "Venez sur twitch et discord vous allez vous mettre bien bien bien",
      "likes": 0,
      "timestamp": 1640217600,
      "parent": "root",
      "is_reply": false
    },
    {
      "author": "@FranciscolucheVietnam1971",
      "author_id": "UC8MoabQgLHDw_cM42klU6ww",
      "text": "Je n’ai rien bité ! 🤔",
      "likes": 1,
      "timestamp": 1640217600,
      "parent": "root",
      "is_reply": false
    },
    {
      "author": "@baiken55",
      "author_id": "UCAKvu3bev0Na87KPDivRrtA",
      "text": "Magnifique conclusion pour un magnifique reportage, Need more",
      "likes": 0,
      "timestamp": 1734912000,
      "parent": "root",
      "is_reply": false
    },
    {
      "author": "@brandondecastro6199",
      "author_id": "UC6S5-kY3jFJRObidEELBcYA",
      "text": "Franchement les frissons qui sont montés au moment où il voulait juste montré à ces paires qui pour ses idées a fais plier les plus grands de ce monde \nJe suis admiratif de ce genre de gens vraiment",
      "likes": 0,
      "timestamp": 1734912000,
      "parent": "root",
      "is_reply": false
    },
    {
      "author": "@Sofianeh94",
      "author_id": "UCTw4KmTHDa9iu0q0IH0MTsg",
      "text": "Encore une fois, super intéressant, mais je suis resté bloqué sur la musique de fond à 5:14, qui la connait ?",
      "likes": 0,
      "timestamp": 1640217600,
      "parent": "root",
      "is_reply": false
    },
    {
      "author": "@aklyss0527",
      "author_id": "UCh7OKmWfVzB3HGaVl0DhP8w",
      "text": "Moi il y a tout de même un truc qui m'échappe on nous dis et certainement a raison que les IA son déjà bien évolué et de l'autre côté des métiers \"cacher\" comme celui de modérateur sur Facebook semble obligatoire. Pourquoi ne pas remplacé ces métier ingrats par des IA 🤔\nPeu que c'est moi qui n'est pas une vision assez poussé de la chose aussi je dis pas apres.",
      "likes": 0,
      "timestamp": 1640217600,
      "parent": "root",
      "is_reply": false
    },
    {
      "author": "@MrMelcx",
      "author_id": "UCsjQnJdFo4AEQVXSRKI-Ufg",
      "text": "La sponso est trop intégrée à la vidéo\nCertes la transition est fluide mais c'est VRAIMENT pas génial de le faire comme ça. Ou alors ajoute un carré \"annonce publicitaire\" quelque part.",
      "likes": 0,
      "timestamp": 1640217600,
      "parent": "root",
      "is_reply": false
    },
    {
      "author": "@ludovicb6489",
      "author_id": "UCu0gFpNu5gem2v8cZobhjzQ",
      "text": "Enchère dans la chambre 731.... Heureusement que ce n'était pas une enchère pour l'unité 731....\n\nBlague débile, j'assume.",
      "likes": 0,
      "timestamp": 1640217600,
      "parent": "root",
      "is_reply": false
    },
    {
      "author": "@NyckylarsonneCH94",
      "author_id": "UCL4QnBoHcVjMHW6n6braavg",
      "text": "Si ça fait 7 qu'il c'est pas assis, juste comment il dort???🤔",
      "likes": 0,
      "timestamp": 1640217600,
      "parent": "root",
      "is_reply": false
    },
    {
      "author": "@alexandrefmx",
      "author_id": "UCgDXAyGVCpbEV50Rzo_Le_w",
      "text": "Attend quoi ? Toi aussi tu dis \"bande D'annonce\" et non \"bande-annonce\" ? (5\"08), je pensais être le seul ?",
      "likes": 0,
      "timestamp": 1640217600,
      "parent": "root",
      "is_reply": false
    },
    {
      "author": "@lil_hoodye",
      "author_id": "UCvOV5Bj7t3CikBiMCOpjT5g",
      "text": "Tes videos sont excellent mais évite les blagues quand même",
      "likes": 0,
      "timestamp": 1640217600,
      "parent": "root",
      "is_reply": false
    },
    {
      "author": "@LeLut1nProduction",
      "author_id": "UCNMuP952_253ItuPXjsQFzQ",
      "text": "T'es sur une chaise ikea en bois🤣 je te plains ouvre un tipee on te fera une cagnotte 😂",
      "likes": 0,
      "timestamp": 1640217600,
      "parent": "root",
      "is_reply": false
    },
    {
      "author": "@hugovaliere1282",
      "author_id": "UCFtDB-uH44N5QDOmeK2Nq_A",
      "text": "2eme",
      "likes": 0,
      "timestamp": 1640217600,
      "parent": "root",
      "is_reply": false
    },
    {
      "author": "@timfrolov7891",
      "author_id": "UCi-2utdb42WDftkEMnbhgug",
      "text": "Ce serait cool si tu captais de quoi tu parlais :/",
      "likes": 1,
      "timestamp": 1640217600,
      "parent": "root",
      "is_reply": false
    },
    {
      "author": "@vgax9264",
      "author_id": "UC3Y7PqgIQEG4jeVFx8_LpYw",
      "text": "Kai Yu..",
      "likes": 2,
      "timestamp": 1640217600,
      "parent": "root",
      "is_reply": false
    },
    {
      "author": "@TexasHotel1",
      "author_id": "UC7AY_lfn7-7HOI8uzAvHcsw",
      "text": "Toujours étonné par les gens qui me parlent informatiques, tech, sécurité etc et qui possèdent une enceinte qui capte tout leur audio chez eux.",
      "likes": 6,
      "timestamp": 1640217600,
      "parent": "root",
      "is_reply": false
    },
    {
      "author": "@suiiiiii5690",
      "author_id": "UCgvufeRqjOaO2N-hLswk8qg",
      "text": "Tes propos sur Twitter sont pathétiques, je dislike.",
      "likes": 0,
      "timestamp": 1640217600,
      "parent": "root",
      "is_reply": false
    },
    {
      "author": "@PxLuffy",
      "author_id": "UC531shTxhUJtMrohup5nvwQ",
      "text": "Super sujet ! D'ailleurs pourrai-tu parler de la guerre USA/CHINE/EUROPE sur l'intelligence artificielle ? Ces 3 puissances mondiales ont elles aussi sauter le pas il y a de ça quelques années et dorénavant ils font la course à savoir qui déposera le plus de brevet et même pire que ça depuis que c'est possible depuis 4-5 ans. L'Europe, la Chine et Les États-Unis font la course à qui possèdera la première intelligence artificielle capable de faire de la recherche sur l'intelligence artificielle. Selon mes enseignants-chercheurs il s'agirait de la prochaine rupture technologique !",
      "likes": 0,
      "timestamp": 1640217600,
      "parent": "root",
      "is_reply": false
    },
    {
      "author": "@sinay297",
      "author_id": "UChNjUh25CW1x3l9Mt6Qkahg",
      "text": "FIRST",
      "likes": 0,
      "timestamp": 1640217600,
      "parent": "root",
      "is_reply": false
    }
  ],
  "error": null
}