{
  "video_id": "ZmFm8r-tt6E",
  "title": "#5   Apprendre à coder en Python pour l'Intelligence Artificielle  Regex, Exceptions, Modules et + !",
  "url": "https://www.youtube.com/watch?v=ZmFm8r-tt6E",
  "comment_count": 5,
  "comments": [
    {
      "author": "@DefendIntelligence",
      "author_id": "UCnEHCrot2HkySxMTmDPhZyg",
      "text": "[REUPLOAD DE LA VIDEO] Diffusé en Live le 19/04/2020 à 18h \r\nSupprimer Accidentellement :(....  Hésitez pas à vous abonner, iker et partager svp, c'est important pour m'aider à faire connaitre la chaine... merci beaucoup.",
      "likes": 3,
      "timestamp": 1608681600,
      "parent": "root",
      "is_reply": false
    },
    {
      "author": "@princegedeon362",
      "author_id": "UC48eigacXr1S3RI5JElLNOQ",
      "text": "Très passionnant.Merci monsieur 🤓",
      "likes": 0,
      "timestamp": 1640217600,
      "parent": "root",
      "is_reply": false
    },
    {
      "author": "@lma7435",
      "author_id": "UCAiQdROt8wKUidkZxKPlnBA",
      "text": "Top, j'espère que d'autres initiés rejoindront en cours de route :) Bon courage",
      "likes": 1,
      "timestamp": 1608681600,
      "parent": "root",
      "is_reply": false
    },
    {
      "author": "@edelweiss7680",
      "author_id": "UCoAOwPnqlTwQmUH0R-3lVtQ",
      "text": "Merci beaucoup pour cette vidéo ! J’ai une remarque : sauf erreur de ma part arg et **kwargs peuvent prendre d’autre  nom. Seules les « * » et « * » avant la variable sont importants.",
      "likes": 1,
      "timestamp": 1640217600,
      "parent": "root",
      "is_reply": false
    },
    {
      "author": "@amichiastephane7740",
      "author_id": "UCKwckH63Fy61tg-8AQoU0_A",
      "text": "J'aimerais savoir pour faire de l'intelligence artificielle. Es ce possible de coder en objets ou coder avec les procédure",
      "likes": 0,
      "timestamp": 1703289600,
      "parent": "root",
      "is_reply": false
    }
  ],
  "error": null
}